Metadata-Version: 2.1
Name: PySeqTest
Version: 1.0.0
Summary: Testes unitários em sequência
Home-page: UNKNOWN
Author: Jaedson Silva
Author-email: imunknowuser@protonmail.com
License: GNU GPL v3.0
Project-URL: Código fonte, https://github.com/jaedsonpys/pyseqtest
Platform: UNKNOWN
